flagparse.py
flagparse-0.0.3.dist-info/LICENSE
flagparse-0.0.3.dist-info/METADATA
flagparse-0.0.3.dist-info/WHEEL
flagparse-0.0.3.dist-info/top_level.txt
flagparse-0.0.3.dist-info/RECORD
