Metadata-Version: 2.1
Name: flagparse
Version: 0.0.3
Summary: flagparse is library to build command-line interfaces
Home-page: https://github.com/ybubnov/flagparse
Author: Yasha Bubnov
Author-email: girokompass@gmail.com
License: UNKNOWN
Keywords: arguments cli parse
Platform: UNKNOWN
Classifier: Intended Audience :: Developers
Classifier: License :: OSI Approved :: MIT License
Classifier: Topic :: Software Development :: Libraries
Classifier: Programming Language :: Python :: 3
Classifier: Programming Language :: Python :: 3.6
Classifier: Programming Language :: Python :: 3.7
Requires-Python: >=3.6
